<?xml version="1.0" encoding="utf-8" ?>
<Defs>

  <ThingDef ParentName="BaseMeleeWeapon_Blunt_Quality">
    <defName>Gerzee_Ram_MeleeWeapon</defName>
    <label>Gerzee Ram</label>
    <description>A huge battering ram crafted to be held only by creatures of great strength, like the Gerzee. Extremely hard-hitting. Despite the careful balancing required to make such a heavy weapon useable, it has a very slow swing recovery.</description>
    <graphicData>
	<texPath>GerzeeRam/GerzeeRam</texPath>
<!--      <texPath>Things/Item/Equipment/WeaponMelee/Mace</texPath> -->
      <graphicClass>Graphic_Single</graphicClass>
    </graphicData>
    <uiIconScale>1.2</uiIconScale>
    <techLevel>Medieval</techLevel>
<!--    <costStuffCount>160</costStuffCount> -->
    <statBases>
      <WorkToMake>17000</WorkToMake><!-- longsword 18000 -->
      <Mass>22</Mass><!--longsword 2 - heavy charge blaster centipede 22--> 
    </statBases>
    <equippedAngleOffset>-80</equippedAngleOffset><!-- -85-->
    <recipeMaker>
      <researchPrerequisite>Smithing</researchPrerequisite>
      <skillRequirements>
        <Crafting>7</Crafting><!-- 5 -->
      </skillRequirements>
    </recipeMaker>
	<equippedStatOffsets>
      <MoveSpeed>-0.8</MoveSpeed>
    </equippedStatOffsets>
	<costList>
      <Steel>160</Steel><!-- longsword is 100-->
    </costList>
<!--    <stuffCategories>
     <li>Steel</li>
	 <li>Woody</li>
    </stuffCategories>-->
    <weaponTags>
	        <li>MedievalMeleeAdvanced</li> <!-- Savior & Altered Mauler pawnkind  ... killer max 200 gold-->
    </weaponTags>
    <tools>
      <li>
        <label>center grip</label>
        <capacities>
          <li>Blunt</li>
        </capacities>
        <power>17</power><!-- mace 9  spear 13... gerzee fist 16.. zeus hammer 15-->
        <cooldownTime>2.5</cooldownTime>
      </li>
      <li>
        <label>head</label>
        <labelUsedInLogging>false</labelUsedInLogging>
        <capacities>
          <li>Blunt</li>
        </capacities>
        <power>30</power><!-- body part often 30, so, will destroy unarmored bodypart at 30. mace 15.7   spear 23 ... warhammer 20 ... zeushamer 31... its blunt.  40 hits through power armor pretty easily-->
        <cooldownTime>4</cooldownTime><!-- spear 2.6 knife 1.5 for slice everything else 2 ... zeus hammer 3--> 
      </li>
    </tools>
  </ThingDef>


<!--
  <ThingDef ParentName="BaseMeleeWeapon_Sharp_Quality">
    <defName>MeleeWeapon_Gladius</defName>
    <label>gladius</label>
    <description>A short sword of ancient design. Good for stabbing or slashing. It's light and nimble, which sometimes lets it beat bigger, heavier weapons.</description>
    <graphicData>
      <texPath>Things/Item/Equipment/WeaponMelee/Gladius</texPath>
      <graphicClass>Graphic_Single</graphicClass>
    </graphicData>
    <uiIconScale>1.2</uiIconScale>
    <techLevel>Medieval</techLevel>
    <costStuffCount>50</costStuffCount>
    <weaponTags>
      <li>MedievalMeleeDecent</li>
    </weaponTags>
    <statBases>
      <WorkToMake>12000</WorkToMake>
      <Mass>0.85</Mass>
    </statBases>
    <equippedAngleOffset>-65</equippedAngleOffset>
    <stuffCategories>
      <li>Metallic</li>
      <li>Woody</li>
    </stuffCategories>
    <tools>
      <li>
        <label>handle</label>
        <capacities>
          <li>Blunt</li>
        </capacities>
        <power>9</power>
        <cooldownTime>2</cooldownTime>
      </li>
      <li>
        <label>point</label>
        <capacities>
          <li>Stab</li>
        </capacities>
        <power>16</power>
        <cooldownTime>2</cooldownTime>
      </li>
      <li>
        <label>edge</label>
        <capacities>
          <li>Cut</li>
        </capacities>
        <power>16</power>
        <cooldownTime>2</cooldownTime>
      </li>
    </tools>
    <recipeMaker>
      <researchPrerequisite>Smithing</researchPrerequisite>
      <skillRequirements>
        <Crafting>3</Crafting>
      </skillRequirements>
    </recipeMaker>
  </ThingDef>

  <ThingDef ParentName="BaseMeleeWeapon_Sharp_Quality">
    <defName>MeleeWeapon_LongSword</defName>
    <label>longsword</label>
    <description>The ancient weapon of kings, the longsword can be used for slashing or stabbing.</description>
    <graphicData>
      <texPath>Things/Item/Equipment/WeaponMelee/LongSword</texPath>
      <graphicClass>Graphic_Single</graphicClass>
    </graphicData>
    <techLevel>Medieval</techLevel>
    <weaponTags>
      <li>MedievalMeleeAdvanced</li>
    </weaponTags>
    <costStuffCount>100</costStuffCount>
    <thingSetMakerTags><li>RewardStandardQualitySuper</li></thingSetMakerTags>
    <statBases>
      <WorkToMake>18000</WorkToMake>
      <Mass>2</Mass>
    </statBases>
    <equippedAngleOffset>-65</equippedAngleOffset>
    <stuffCategories>
      <li>Metallic</li>
      <li>Woody</li>
    </stuffCategories>
    <tools>
      <li>
        <label>handle</label>
        <capacities>
          <li>Blunt</li>
        </capacities>
        <power>9</power>
        <cooldownTime>2</cooldownTime>
      </li>
      <li>
        <label>point</label>
        <capacities>
          <li>Stab</li>
        </capacities>
        <power>23</power>
        <cooldownTime>2.6</cooldownTime>
      </li>
      <li>
        <label>edge</label>
        <capacities>
          <li>Cut</li>
        </capacities>
        <power>23</power>
        <cooldownTime>2.6</cooldownTime>
      </li>
    </tools>
    <recipeMaker>
      <researchPrerequisite>LongBlades</researchPrerequisite>
      <skillRequirements>
        <Crafting>5</Crafting>
      </skillRequirements>
    </recipeMaker>
  </ThingDef>
-->
  
</Defs>